.bzrignore
LICENSE
MANIFEST.in
setup.py
nose_scenario/__init__.py
nose_scenario/adapt.py
nose_scenario/nose_plugin.py
nose_scenario.egg-info/PKG-INFO
nose_scenario.egg-info/SOURCES.txt
nose_scenario.egg-info/dependency_links.txt
nose_scenario.egg-info/entry_points.txt
nose_scenario.egg-info/not-zip-safe
nose_scenario.egg-info/requires.txt
nose_scenario.egg-info/top_level.txt
test/__init__.py
test/sample_scenarios.py
test/test_testclass.py
test/test_unittest.py