Metadata-Version: 1.0
Name: nose-scenario
Version: 0.1.3
Summary: test scenario adaptation plugin for nose
Home-page: http://cheeseshop.python.org/pypi/nose_scenario/
Author: Ben Finney
Author-email: ben+python@benfinney.id.au
License: GPL
Keywords: nose plugin test unittest scenario adapt
Platform: UNKNOWN
Classifier: Development Status :: 3 - Alpha
Classifier: License :: OSI Approved :: GNU General Public License (GPL)
Classifier: Programming Language :: Python
Classifier: Topic :: Software Development :: Testing
Classifier: Operating System :: OS Independent
Classifier: Intended Audience :: Developers
